netbox_entity_relationship/.gitignore
netbox_entity_relationship/__init__.py
netbox_entity_relationship/choices.py
netbox_entity_relationship/diagram.py
netbox_entity_relationship/forms.py
netbox_entity_relationship/navigation.py
netbox_entity_relationship/templates/netbox_entity_relationship/netbox_entity_relationship_form.html
netbox_entity_relationship/templates/netbox_entity_relationship/netbox_entity_relationship_netbox.html
netbox_entity_relationship/templates/netbox_entity_relationship/netbox_entity_relationship_render.html
netbox_entity_relationship/urls.py
netbox_entity_relationship/views.py
netbox_entity_relationship-0.1.2.dist-info/METADATA
netbox_entity_relationship-0.1.2.dist-info/WHEEL
netbox_entity_relationship-0.1.2.dist-info/RECORD
