Metadata-Version: 2.1
Name: netbox-entity-relationship
Version: 0.1.2
Summary: Plugin for Entity Relationship Diagram
Author: apishark
Author-email: support@opticoreit.com
Requires-Python: >=3.8,<4.0
Classifier: Programming Language :: Python :: 3
Classifier: Programming Language :: Python :: 3.8
Classifier: Programming Language :: Python :: 3.9
Classifier: Programming Language :: Python :: 3.10
Classifier: Programming Language :: Python :: 3.11
Requires-Dist: django-extensions (>=3.2.1,<4.0.0)
Requires-Dist: pygraphviz (>=1.10,<2.0)
